ibmodules
