Metadata-Version: 2.1
Name: ibmodules
Version: 0.1.2
Summary: ibmodules for "interesting bit" operations
Home-page: https://github.com/vin01/ibmodules
Author: Bhou Gonzas
Author-email: vhbhousuber@protonmail.com
Project-URL: Documentation, https://github.com/vin01/ibmodules
Project-URL: Bug Reports, https://github.com/vin01/ibmodules/issues
Project-URL: Source Code, https://github.com/vin01/ibmodules
Keywords: ibmodules,pypi,package
Classifier: Development Status :: 5 - Production/Stable
Classifier: Intended Audience :: Developers
Classifier: Topic :: Software Development :: Build Tools
Classifier: Programming Language :: Python :: 3
Classifier: Programming Language :: Python :: 3.6
Classifier: Programming Language :: Python :: 3.7
Classifier: Programming Language :: Python :: 3.8
Classifier: Programming Language :: Python :: 3.9
Classifier: Programming Language :: Python :: 3 :: Only
Classifier: License :: OSI Approved :: MIT License
Classifier: Operating System :: OS Independent
Requires-Python: >=3.6
Provides-Extra: dev
License-File: LICENSE
